aws_cost_optimization_13/__init__.py
aws_cost_optimization_13/_cloudwatch_costing.py
aws_cost_optimization_13/_ec2_costing.py
aws_cost_optimization_13/_elb_costing.py
aws_cost_optimization_13/_kms_costing.py
aws_cost_optimization_13/_rds_costing.py
aws_cost_optimization_13/_ri_recommendations.py
aws_cost_optimization_13/_savings_plan.py
aws_cost_optimization_13/utils.py
aws_cost_optimization_13-0.2.12.dist-info/LICENCE
aws_cost_optimization_13-0.2.12.dist-info/METADATA
aws_cost_optimization_13-0.2.12.dist-info/WHEEL
aws_cost_optimization_13-0.2.12.dist-info/top_level.txt
aws_cost_optimization_13-0.2.12.dist-info/RECORD
